torchax/CONTRIBUTING.md
torchax/__init__.py
torchax/amp.py
torchax/checkpoint.py
torchax/config.py
torchax/decompositions.py
torchax/device_module.py
torchax/export.py
torchax/flax.py
torchax/interop.py
torchax/mesh_util.py
torchax/tensor.py
torchax/train.py
torchax/types.py
torchax/util.py
torchax/view.py
torchax/ops/__init__.py
torchax/ops/jaten.py
torchax/ops/jax_reimplement.py
torchax/ops/jc10d.py
torchax/ops/jimage.py
torchax/ops/jlibrary.py
torchax/ops/jtorch.py
torchax/ops/jtorchvision_nms.py
torchax/ops/mappings.py
torchax/ops/op_base.py
torchax/ops/ops_registry.py
torchax-0.0.9.dist-info/METADATA
torchax-0.0.9.dist-info/WHEEL
torchax-0.0.9.dist-info/licenses/LICENSE
torchax-0.0.9.dist-info/RECORD
