Metadata-Version: 2.4
Name: torchax
Version: 0.0.9
Summary: torchax is a library for running Jax and PyTorch together
Project-URL: Homepage, https://github.com/google/torchax
Author-email: Han Qi <qihan.dev@gmail.com>, Google Cloud Inference Team <cmcs-inference-eng@google.com>
License:                                  Apache License
License-File: LICENSE
Classifier: Development Status :: 3 - Alpha
Classifier: Intended Audience :: Developers
Classifier: Intended Audience :: Education
Classifier: Intended Audience :: Science/Research
Classifier: License :: OSI Approved :: Apache Software License
Classifier: Programming Language :: Python :: 3.11
Classifier: Programming Language :: Python :: 3.12
Classifier: Programming Language :: Python :: 3.13
Classifier: Topic :: Scientific/Engineering
Classifier: Topic :: Scientific/Engineering :: Artificial Intelligence
Classifier: Topic :: Scientific/Engineering :: Mathematics
Classifier: Topic :: Software Development
Classifier: Topic :: Software Development :: Libraries
Classifier: Topic :: Software Development :: Libraries :: Python Modules
Requires-Python: >=3.11
Provides-Extra: cpu
Requires-Dist: jax[cpu]; extra == 'cpu'
Requires-Dist: jax[cpu]>=0.6.2; extra == 'cpu'
Provides-Extra: cuda
Requires-Dist: jax[cpu]>=0.6.2; extra == 'cuda'
Requires-Dist: jax[cuda12]; extra == 'cuda'
Provides-Extra: odml
Requires-Dist: jax[cpu]; extra == 'odml'
Requires-Dist: jax[cpu]>=0.6.2; extra == 'odml'
Provides-Extra: tpu
Requires-Dist: jax[cpu]>=0.6.2; extra == 'tpu'
Requires-Dist: jax[tpu]; extra == 'tpu'
